rtl/lfsr.sv
module lfsr(
    input clk,
    input nreset,
    input [7:1] in_data,
    output logic [7:1] shifter_output  
);



always @(posedge clk or negedge nreset) begin
    if(!nreset) begin
    shifter_output<=7'b1111111;
    end
    else begin
    shifter_output<=in_data;
    end 
end

endmodule

rtl/xor_logic.sv
module xor_logic(
    input [7:1]shifter_output, //s1-s7
    output [15:0]lfsr //lfsr0-lfsr15
);

assign lfsr[0]=shifter_output[4]^shifter_output[7];
assign lfsr[1]=shifter_output[3]^shifter_output[6];
assign lfsr[2]=shifter_output[2]^shifter_output[5];
assign lfsr[3]=shifter_output[1]^shifter_output[4];
assign lfsr[4]=shifter_output[3]^shifter_output[4]^shifter_output[7];
assign lfsr[5]=shifter_output[2]^shifter_output[3]^shifter_output[6];
assign lfsr[6]=shifter_output[1]^shifter_output[2]^shifter_output[5];
assign lfsr[7]=shifter_output[1]^shifter_output[7];
assign lfsr[8]=shifter_output[4]^shifter_output[6]^shifter_output[7];
assign lfsr[9]=shifter_output[3]^shifter_output[5]^shifter_output[6];
assign lfsr[10]=shifter_output[2]^shifter_output[4]^shifter_output[5];
assign lfsr[11]=shifter_output[1]^shifter_output[3]^shifter_output[4];
assign lfsr[12]=shifter_output[2]^shifter_output[3]^shifter_output[4]^shifter_output[7];
assign lfsr[13]=shifter_output[1]^shifter_output[2]^shifter_output[3]^shifter_output[6];
assign lfsr[14]=shifter_output[1]^shifter_output[2]^shifter_output[4]^shifter_output[5]^shifter_output[7];
assign lfsr[15]=shifter_output[1]^shifter_output[3]^shifter_output[6]^shifter_output[7];

endmodule

rtl/scrambler_16bit.sv
module scrambler_16bit(
    input valid,
    input clk,
    input nreset,
    input [15:0] data_in,
    output [63:0] data_out_64bit,
    output [47:0] data_out_48bit,
    output [31:0] data_out_32bit,
    output [15:0] data_out_16bit
);

wire [7:1]mux_output; //the wire that goes inside the lfsr
wire [7:1] shifter_output; //this wire goes from outside the shifters inside the xor_logic
wire [15:0] xor_logic_output; //this wire goes from outside the xor_logic to the output_xor,delivering all the 64 lfsr's
//wire [31:0] xor_logic_output_test; // just like the regular one,but for tests.
wire [7:1]current_stage;
wire [7:1]next_stage;


//module wires
wire [15:0]lfsr1;
wire [15:0]lfsr2;
wire [15:0]lfsr3;
wire [15:0]lfsr4;
//the reason for the explicitness of next stage is that
// bcz for current stage the input stay the same and shouldnt be reversed as the new stage should
assign current_stage=shifter_output;
assign next_stage[1]=xor_logic_output[15];
assign next_stage[2]=xor_logic_output[14];
assign next_stage[3]=xor_logic_output[13];
assign next_stage[4]=xor_logic_output[12];
assign next_stage[5]=xor_logic_output[11];
assign next_stage[6]=xor_logic_output[10];
assign next_stage[7]=xor_logic_output[9];

assign mux_output=valid ? next_stage : current_stage; 

//my test for each output
assign data_out_16bit[15:0]=xor_logic_output[15:0] ^data_in[15:0]; //output xor



xor_logic xor_logic1(
    .shifter_output(shifter_output),
    .lfsr(lfsr1)
);

xor_logic xor_logic2(
    .shifter_output({lfsr1[9],lfsr1[10],lfsr1[11],lfsr1[12],lfsr1[13],lfsr1[14],lfsr1[15]}),
    .lfsr(lfsr2)
);

xor_logic xor_logic3(
    .shifter_output({lfsr2[9],lfsr2[10],lfsr2[11],lfsr2[12],lfsr2[13],lfsr2[14],lfsr2[15]}),
    .lfsr(lfsr3)
);

xor_logic xor_logic4(
    .shifter_output({lfsr3[9],lfsr3[10],lfsr3[11],lfsr3[12],lfsr3[13],lfsr3[14],lfsr3[15]}),
    .lfsr(lfsr4)
);

lfsr lfsr_machine(
    .clk(clk),
    .nreset(nreset),
    .in_data(mux_output),
    .shifter_output(shifter_output)
);

assign xor_logic_output[15:0]=lfsr1[15:0];
//assign xor_logic_output[31:16]=lfsr2[15:0];
//assign xor_logic_output[47:32]=lfsr3[15:0];
//assign xor_logic_output[63:48]=lfsr4[15:0];


 
endmodule






/*


module scrambler_16bit(
    input [15:0] data_in,
    input clk,
    input valid,
    input nreset,
    output [15:0] data_out
);


//connecting between lfsr s output to xor_logic s input 
wire [7:1]shifter_output;
//connecting between the xor_logic cloud([15:0]lfsr) to the output xor 
wire [15:0]lfsr_output;
//connecting between the output of the mux(input of the lfsr) to the input of the mux
wire [7:1]lfsr_data_in;
wire [7:1]mux_input;
//from the output of the xor logic to the outside of the mux
assign mux_input[1] = lfsr_output[15];
assign mux_input[2] = lfsr_output[14];
assign mux_input[3] = lfsr_output[13];
assign mux_input[4] = lfsr_output[12];
assign mux_input[5] = lfsr_output[11];
assign mux_input[6] = lfsr_output[10];
assign mux_input[7] = lfsr_output[9];

//Creating validation mux for input data
assign lfsr_data_in= valid? mux_input : shifter_output ;
//creating the output xor 
assign data_out=lfsr_output ^ data_in;


xor_logic xor_logic1(
    .shifter_output(shifter_output),
    .lfsr(lfsr_output)
);

lfsr lfsr1(
    .clk(clk),
    .nreset(nreset),
    .in_data(lfsr_data_in),
    .shifter_output(shifter_output)
);



endmodule

*/

rtl/scrambler_64bit.sv
module scrambler_64bit(
    input valid,
    input clk,
    input nreset,
    input [63:0] data_in,
    output [63:0] data_out_64bit,
    output [47:0] data_out_48bit,
    output [31:0] data_out_32bit
);

wire [7:1]mux_output; //the wire that goes inside the lfsr
wire [7:1] shifter_output; //this wire goes from outside the shifters inside the xor_logic
wire [63:0] xor_logic_output; //this wire goes from outside the xor_logic to the output_xor,delivering all the 64 lfsr's
//wire [31:0] xor_logic_output_test; // just like the regular one,but for tests.
wire [7:1]current_stage;
wire [7:1]next_stage;


//module wires
wire [15:0]lfsr1;
wire [15:0]lfsr2;
wire [15:0]lfsr3;
wire [15:0]lfsr4;
//the reason for the explicitness of next stage is that
// bcz for current stage the input stay the same and shouldnt be reversed as the new stage should
assign current_stage=shifter_output;
assign next_stage[1]=xor_logic_output[63];
assign next_stage[2]=xor_logic_output[62];
assign next_stage[3]=xor_logic_output[61];
assign next_stage[4]=xor_logic_output[60];
assign next_stage[5]=xor_logic_output[59];
assign next_stage[6]=xor_logic_output[58];
assign next_stage[7]=xor_logic_output[57];

assign mux_output=valid ? next_stage : current_stage; 

//my test for each output
assign data_out_64bit[63:0]=xor_logic_output[63:0] ^data_in[63:0]; //output xor



xor_logic xor_logic1(
    .shifter_output(shifter_output),
    .lfsr(lfsr1)
);

xor_logic xor_logic2(
    .shifter_output({lfsr1[9],lfsr1[10],lfsr1[11],lfsr1[12],lfsr1[13],lfsr1[14],lfsr1[15]}),
    .lfsr(lfsr2)
);

xor_logic xor_logic3(
    .shifter_output({lfsr2[9],lfsr2[10],lfsr2[11],lfsr2[12],lfsr2[13],lfsr2[14],lfsr2[15]}),
    .lfsr(lfsr3)
);

xor_logic xor_logic4(
    .shifter_output({lfsr3[9],lfsr3[10],lfsr3[11],lfsr3[12],lfsr3[13],lfsr3[14],lfsr3[15]}),
    .lfsr(lfsr4)
);

lfsr lfsr_machine(
    .clk(clk),
    .nreset(nreset),
    .in_data(mux_output),
    .shifter_output(shifter_output)
);

assign xor_logic_output[15:0]=lfsr1[15:0];
assign xor_logic_output[31:16]=lfsr2[15:0];
assign xor_logic_output[47:32]=lfsr3[15:0];
assign xor_logic_output[63:48]=lfsr4[15:0];


 
endmodule

rtl/clock_divider.sv
module clock_divider(
    input clk_in,
    input nreset,
    output reg clk_out
);

always @(posedge clk_in or negedge nreset) begin
    if(!nreset) begin
        clk_out<=1'b0;
    end
    else begin
        clk_out<=~clk_out;
    end
end





endmodule

rtl/input_sampler.sv
module input_sampler(
    input clk,
    input nreset,
    input valid,
    input [15:0]data_in_16bit,
    input [63:0]data_in_64bit,
    output logic [63:0] data_sampled_64bit,
    output logic [15:0] data_sampled_16bit,
    output logic valid_sampled,
    output logic nreset_sampled 
);

always @(posedge clk or negedge nreset) begin
    if(!nreset) begin
        data_sampled_16bit<=16'b0;
        data_sampled_64bit<=64'b0;
        valid_sampled<=1'b0;
        nreset_sampled<=1'b0;        
    end
    else begin
        data_sampled_16bit<=data_in_16bit;
        data_sampled_64bit<=data_in_64bit;
        valid_sampled<=valid;
        nreset_sampled<=nreset;
        
    end
end

endmodule

rtl/scrambler_tb.sv
`timescale 1ns / 1ps

module scrambler_tb; // no ports

    // defining inputs
    reg nreset;
    reg valid;

    //InputSampler- DUT2
    reg [15:0]data_in_input_sampler_16bit;
    reg [63:0]data_in_input_sampler_64bit;    
    wire nreset_input_sampler;
    wire valid_input_sampler;
    wire [15:0]data_out_input_sampler_16bit;
    wire [63:0]data_out_input_sampler_64bit;
    

    //scrambler_64bit -DUT0
    reg [63:0] inputs_64bit [0:999];
    reg [63:0] expected_output_64bit [0:999];
    reg [63:0] golden_lfsr_bits_64bit [0:999];//for every input the lfsr is calculated-1000 inputs,16 lfsr bits each
    wire [63:0] data_out_64bit;
    //probing for DUT0
    wire [63:0] xor_logic_output_DUT0;
    assign xor_logic_output_DUT0=DUT0.xor_logic_output;    
    // Golden model state: [0]=s1 .. [6]=s7
    reg  [7:1]  golden_shifter;
    reg         golden_bit;
    reg  [63:0] golden_out_64bit;
    integer pass_count, fail_count, i,j;
    integer seed;
    
    //scrambler-16bit- DUT1
    reg [15:0] inputs_16bit [0:999];
    reg [15:0] expected_output_16bit [0:999];
    reg [15:0] golden_lfsr_bits_16bit [0:999];//for every input the lfsr is calculated-1000 inputs,16 lfsr bits each
    reg  [15:0] golden_out_16bit;
    wire [15:0] data_out_16bit;
    //probing for DUT1
    wire [15:0] xor_logic_output_DUT1;
    assign xor_logic_output_DUT1=DUT1.xor_logic_output;
    
    //clockDivider TB input and output
    reg clk;
    wire clk_out_for_clockDivider;



    input_sampler DUT2(
        .clk(clk_out_for_clockDivider),
        .nreset(nreset),
        .valid(valid),
        .data_in_16bit(data_in_input_sampler_16bit),
        .data_in_64bit(data_in_input_sampler_64bit),
        .data_sampled_16bit(data_out_input_sampler_16bit),
        .data_sampled_64bit(data_out_input_sampler_64bit),
        .valid_sampled(valid_input_sampler),
        .nreset_sampled(nreset_input_sampler)
    );

    clock_divider DUT3(
        .clk_in(clk),
        .nreset(nreset),
        .clk_out(clk_out_for_clockDivider)
    );    

    scrambler_64bit DUT0(
        .clk(clk_out_for_clockDivider),
        .valid(valid_input_sampler),
        .nreset(nreset),
        .data_in(data_out_input_sampler_64bit),
        .data_out_64bit(data_out_64bit),
        .data_out_48bit(),
        .data_out_32bit()
    );

    scrambler_16bit DUT1(
        .clk(clk_out_for_clockDivider),
        .valid(valid_input_sampler),
        .nreset(nreset),
        .data_in(data_out_input_sampler_16bit),
        .data_out_64bit(),
        .data_out_48bit(),
        .data_out_32bit(),
        .data_out_16bit(data_out_16bit)
    );

    always #5 clk=~clk;

    initial begin
        $dumpfile("scrambler_tb.vcd");
        $dumpvars(0, scrambler_tb);

        clk=0;
        pass_count = 0;
        fail_count = 0;

        nreset=0;
        #20;
        nreset=1'b1;
        valid=0;
        @(posedge clk_out_for_clockDivider);  

        if(!$value$plusargs("seed=%d", seed)) seed=1;
        seed=$random(seed);

        //Phase 1:generating 1000 inputs,and calculating expected output
        golden_shifter = 7'b1111111; // same as DUT async-reset value
        for(i=0;i<1000;i=i+1) begin 
            inputs_64bit[i]=$random(seed) & 64'hFFFFFFFFFFFFFFFF;
            golden_out_64bit=0;
            for (j=0;j<64;j=j+1) begin
                golden_bit=golden_shifter[4]^ golden_shifter[7];//calculate the next lfsr
                golden_lfsr_bits_64bit[i][j]=golden_bit;// the current lfsr is being stored
                golden_out_64bit[j]=golden_bit^inputs_64bit[i][j];
                golden_shifter={golden_shifter[6:1],golden_bit};
            end
            //taking the golden out fronm the previous for loop(16bit) and inserting it inside row i,every row holds 16bit
            expected_output_64bit[i]=golden_out_64bit;
        end
        #50;
        for(i=0;i<1000;i=i+1) begin
            //sampling the input into the inputSampler and from there to the DUT0            
            data_in_input_sampler_64bit=inputs_64bit[i];
            valid=1'b1;
            @(posedge clk_out_for_clockDivider);
            #1;
            //comparing expected data out to the actual data out
            if(data_out_64bit==expected_output_64bit[i]) begin
            pass_count=pass_count+1;
            end
            else begin
                $display("Cycle %4d:FAIL (expected=%04X, actual=%04X)",i,expected_output_64bit[i],data_out_64bit);
                fail_count=fail_count+1;
            end
            if(xor_logic_output_DUT0!= golden_lfsr_bits_64bit[i])
            $display("Cycle %4d: LFSR MISMATCH (sequential=%04X, parallel=%04X)",i, golden_lfsr_bits_64bit[i], DUT0.xor_logic_output);
        end
        #20;
        $display("\n%0d PASSED, %0d FAILED", pass_count,fail_count);


        //Now for the 16bit scrambler
        nreset=0;
        #20;
        nreset=1'b1;
        valid=0;
        @(posedge clk_out_for_clockDivider);  
        if(!$value$plusargs("seed=%d", seed)) seed=1;
        seed=$random(seed);
        //Phase 1:generating 1000 inputs,and calculating expected output
        golden_shifter = 7'b1111111; // same as DUT async-reset value
        for(i=0;i<1000;i=i+1) begin 
            inputs_16bit[i]=$random(seed) & 16'hFFFF;
            golden_out_16bit=0;
            for (j=0;j<16;j=j+1) begin
                golden_bit=golden_shifter[4]^ golden_shifter[7];//calculate the next lfsr
                golden_lfsr_bits_16bit[i][j]=golden_bit;// the current lfsr is being stored
                golden_out_16bit[j]=golden_bit^inputs_16bit[i][j];
                golden_shifter={golden_shifter[6:1],golden_bit};
            end
            //taking the golden out fronm the previous for loop(16bit) and inserting it inside row i,every row holds 16bit
            expected_output_16bit[i]=golden_out_16bit;
        end
        #50;
        for(i=0;i<1000;i=i+1) begin
            //sampling the input into the inputSampler and from there to the DUT1
            data_in_input_sampler_16bit=inputs_16bit[i];
            valid=1'b1;
            @(posedge clk_out_for_clockDivider);
            #1;
            //comparing expected data out to the actual data out
            if(data_out_16bit==expected_output_16bit[i]) begin
            pass_count=pass_count+1;
            end
            else begin
                $display("Cycle %4d:FAIL (expected=%04X, actual=%04X)",i,expected_output_16bit[i],data_out_16bit);
                fail_count=fail_count+1;
            end
            if(xor_logic_output_DUT1!= golden_lfsr_bits_16bit[i])
            $display("Cycle %4d: LFSR MISMATCH (sequential=%04X, parallel=%04X)",i, golden_lfsr_bits_16bit[i], DUT1.xor_logic_output);
        end
        #20;
        $display("\n%0d PASSED, %0d FAILED", pass_count,fail_count);
        $finish;  
    end

endmodule

rtl/scrambler_tb.vcd
$date
	Tue Aug 04 15:04:54 2026
$end
$version
	Icarus Verilog
$end
$timescale
	1ps
$end
$scope module scrambler_tb $end
$var wire 64 ! xor_logic_output_DUT0 [63:0] $end
$var wire 16 " xor_logic_output_DUT1 [15:0] $end
$var wire 1 # valid_input_sampler $end
$var wire 1 $ nreset_input_sampler $end
$var wire 64 % data_out_input_sampler_64bit [63:0] $end
$var wire 16 & data_out_input_sampler_16bit [15:0] $end
$var wire 64 ' data_out_64bit [63:0] $end
$var wire 16 ( data_out_16bit [15:0] $end
$var wire 1 ) clk_out_for_clockDivider $end
$var reg 1 * clk $end
$var reg 16 + data_in_input_sampler_16bit [15:0] $end
$var reg 64 , data_in_input_sampler_64bit [63:0] $end
$var reg 1 - golden_bit $end
$var reg 16 . golden_out_16bit [15:0] $end
$var reg 64 / golden_out_64bit [63:0] $end
$var reg 7 0 golden_shifter [7:1] $end
$var reg 1 1 nreset $end
$var reg 1 2 valid $end
$var integer 32 3 fail_count [31:0] $end
$var integer 32 4 i [31:0] $end
$var integer 32 5 j [31:0] $end
$var integer 32 6 pass_count [31:0] $end
$var integer 32 7 seed [31:0] $end
$scope module DUT0 $end
$var wire 7 8 current_stage [7:1] $end
$var wire 32 9 data_out_32bit [31:0] $end
$var wire 48 : data_out_48bit [47:0] $end
$var wire 64 ; data_out_64bit [63:0] $end
$var wire 1 1 nreset $end
$var wire 64 < xor_logic_output [63:0] $end
$var wire 1 # valid $end
$var wire 7 = shifter_output [7:1] $end
$var wire 7 > next_stage [7:1] $end
$var wire 7 ? mux_output [7:1] $end
$var wire 16 @ lfsr4 [15:0] $end
$var wire 16 A lfsr3 [15:0] $end
$var wire 16 B lfsr2 [15:0] $end
$var wire 16 C lfsr1 [15:0] $end
$var wire 64 D data_in [63:0] $end
$var wire 1 ) clk $end
$scope module lfsr_machine $end
$var wire 7 E in_data [7:1] $end
$var wire 1 1 nreset $end
$var wire 1 ) clk $end
$var reg 7 F shifter_output [7:1] $end
$upscope $end
$scope module xor_logic1 $end
$var wire 7 G shifter_output [7:1] $end
$var wire 16 H lfsr [15:0] $end
$upscope $end
$scope module xor_logic2 $end
$var wire 7 I shifter_output [7:1] $end
$var wire 16 J lfsr [15:0] $end
$upscope $end
$scope module xor_logic3 $end
$var wire 7 K shifter_output [7:1] $end
$var wire 16 L lfsr [15:0] $end
$upscope $end
$scope module xor_logic4 $end
$var wire 7 M shifter_output [7:1] $end
$var wire 16 N lfsr [15:0] $end
$upscope $end
$upscope $end
$scope module DUT1 $end
$var wire 7 O current_stage [7:1] $end
$var wire 16 P data_out_16bit [15:0] $end
$var wire 32 Q data_out_32bit [31:0] $end
$var wire 48 R data_out_48bit [47:0] $end
$var wire 64 S data_out_64bit [63:0] $end
$var wire 1 1 nreset $end
$var wire 16 T xor_logic_output [15:0] $end
$var wire 1 # valid $end
$var wire 7 U shifter_output [7:1] $end
$var wire 7 V next_stage [7:1] $end
$var wire 7 W mux_output [7:1] $end
$var wire 16 X lfsr4 [15:0] $end
$var wire 16 Y lfsr3 [15:0] $end
$var wire 16 Z lfsr2 [15:0] $end
$var wire 16 [ lfsr1 [15:0] $end
$var wire 16 \ data_in [15:0] $end
$var wire 1 ) clk $end
$scope module lfsr_machine $end
$var wire 7 ] in_data [7:1] $end
$var wire 1 1 nreset $end
$var wire 1 ) clk $end
$var reg 7 ^ shifter_output [7:1] $end
$upscope $end
$scope module xor_logic1 $end
$var wire 7 _ shifter_output [7:1] $end
$var wire 16 ` lfsr [15:0] $end
$upscope $end
$scope module xor_logic2 $end
$var wire 7 a shifter_output [7:1] $end
$var wire 16 b lfsr [15:0] $end
$upscope $end
$scope module xor_logic3 $end
$var wire 7 c shifter_output [7:1] $end
$var wire 16 d lfsr [15:0] $end
$upscope $end
$scope module xor_logic4 $end
$var wire 7 e shifter_output [7:1] $end
$var wire 16 f lfsr [15:0] $end
$upscope $end
$upscope $end
$scope module DUT2 $end
$var wire 16 g data_in_16bit [15:0] $end
$var wire 64 h data_in_64bit [63:0] $end
$var wire 1 1 nreset $end
$var wire 1 2 valid $end
$var wire 1 ) clk $end
$var reg 16 i data_sampled_16bit [15:0] $end
$var reg 64 j data_sampled_64bit [63:0] $end
$var reg 1 $ nreset_sampled $end
$var reg 1 # valid_sampled $end
$upscope $end
$scope module DUT3 $end
$var wire 1 * clk_in $end
$var wire 1 1 nreset $end
$var reg 1 ) clk_out $end
$upscope $end
$upscope $end
$enddefinitions $end
$comment Show the parameter values. $end
$dumpall
$end
#0
$dumpvars
b0 j
b0 i
bx h
bx g
b11000001101101 f
b101110 e
b111010001100100 d
b10 c
b100000010010011 b
b1110010 a
b100111101110000 `
b1111111 _
b1111111 ^
b1111111 ]
b0 \
b100111101110000 [
b100000010010011 Z
b111010001100100 Y
b11000001101101 X
b1111111 W
b1110010 V
b1111111 U
b100111101110000 T
bz S
bz R
bz Q
b100111101110000 P
b1111111 O
b11000001101101 N
b101110 M
b111010001100100 L
b10 K
b100000010010011 J
b1110010 I
b100111101110000 H
b1111111 G
b1111111 F
b1111111 E
b0 D
b100111101110000 C
b100000010010011 B
b111010001100100 A
b11000001101101 @
b1111111 ?
b1100 >
b1111111 =
b11000001101101011101000110010001000000100100110100111101110000 <
b11000001101101011101000110010001000000100100110100111101110000 ;
bz :
bz 9
b1111111 8
bx 7
b0 6
bx 5
bx 4
b0 3
x2
01
bx 0
bx /
bx .
x-
bx ,
bx +
0*
0)
b100111101110000 (
b11000001101101011101000110010001000000100100110100111101110000 '
b0 &
b0 %
0$
0#
b100111101110000 "
b11000001101101011101000110010001000000100100110100111101110000 !
$end
#5000
1*
#10000
0*
#15000
1*
#20000
0*
02
11
#25000
bx '
bx ;
bx (
bx P
1$
bx %
bx D
bx j
bx &
bx \
bx i
0-
b1000000 5
b11101100010100101111101010100010010001001110111001100011110101 /
b1111101000 4
b1011100 0
b1001010111101011100110011111000 7
1)
1*
#30000
0*
#35000
0)
1*
#40000
0*
#45000
1)
1*
#50000
0*
#55000
0)
1*
#60000
0*
#65000
1)
1*
#70000
0*
#75000
0)
1*
12
b10100110110010101010100001001101 ,
b10100110110010101010100001001101 h
b0 4
#80000
0*
#85000
b1110010 W
b1110010 ]
b1100 ?
b1100 E
b11000001101101011101000110010011100110010110011110011100111101 '
b11000001101101011101000110010011100110010110011110011100111101 ;
1#
b10100110110010101010100001001101 %
b10100110110010101010100001001101 D
b10100110110010101010100001001101 j
1)
1*
#86000
b10000000101101011111110000000001 ,
b10000000101101011111110000000001 h
b1 4
b1 6
#90000
0*
#95000
0)
1*
#100000
0*
#105000
b1111110 ?
b1111110 E
b1111110 >
b1110011100101011 X
b1110011100101011 f
b111111100011101 @
b111111100011101 N
b1100 e
b1010001 M
b11000001101101 Y
b11000001101101 d
b1000101001011111 A
b1000101001011111 L
b101110 c
b101010 K
b111010001100100 Z
b111010001100100 b
b101010000101101 B
b101010000101101 J
b10 W
b10 ]
b10 a
b10 V
b1100111 I
b111111100011101100010100101111101010100001011011110011100101011 !
b111111100011101100010100101111101010100001011011110011100101011 <
b100000010010011 "
b100000010010011 T
b100000010010011 [
b100000010010011 `
b1110011100101011 C
b1110011100101011 H
b111111100011101100010100101111111010100100110000001101100101010 '
b111111100011101100010100101111111010100100110000001101100101010 ;
b1110010 O
b1110010 U
b1110010 ^
b1110010 _
b1100 8
b1100 =
b1100 F
b1100 G
b10000000101101011111110000000001 %
b10000000101101011111110000000001 D
b10000000101101011111110000000001 j
1)
1*
#106000
b1001011010100100001101110010110 ,
b1001011010100100001101110010110 h
b10 4
b10 6
#110000
0*
#115000
0)
1*
#120000
0*
#125000
b11001 ?
b11001 E
b11001 >
b1001100000110110 @
b1001100000110110 N
b101010000101101 X
b101010000101101 f
b1011101 M
b1100111 e
b1011101000110010 A
b1011101000110010 L
b1110011100101011 Y
b1110011100101011 d
b100 K
b1100 c
b10000001001001 B
b10000001001001 J
b11000001101101 Z
b11000001101101 b
b101110 W
b101110 ]
b1100101 I
b101110 a
b101110 V
b1001100000110110101110100011001000100000010010011010011110111000 !
b1001100000110110101110100011001000100000010010011010011110111000 <
b1010011110111000 C
b1010011110111000 H
b111010001100100 "
b111010001100100 T
b111010001100100 [
b111010001100100 `
b1001100000110110101110100011001001101011000110111011110000101110 '
b1001100000110110101110100011001001101011000110111011110000101110 ;
b1001011010100100001101110010110 %
b1001011010100100001101110010110 D
b1001011010100100001101110010110 j
b1111110 8
b1111110 =
b1111110 F
b1111110 G
b10 O
b10 U
b10 ^
b10 _
1)
1*
#126000
b10010110000001110101011000101100 ,
b10010110000001110101011000101100 h
b11 4
b11 6
#130000
0*
#135000
0)
1*
#140000
0*
#145000
b1111100 ?
b1111100 E
b1111100 >
b1000101001011111 X
b1000101001011111 f
b11111110001110 @
b11111110001110 N
b101010 e
b100011 M
b101010000101101 Y
b101010000101101 d
b1100010100101111 A
b1100010100101111 L
b1100111 c
b1010101 K
b1110011100101011 Z
b1110011100101011 b
b1010101000010110 B
b1010101000010110 J
b1100 W
b1100 ]
b1100 a
b1100 V
b1001111 I
b11111110001110110001010010111110101010000101101111001110010101 !
b11111110001110110001010010111110101010000101101111001110010101 <
b11000001101101 "
b11000001101101 T
b11000001101101 [
b11000001101101 `
b1111001110010101 C
b1111001110010101 H
b11111110001110110001010010111100111100000100011010010110111001 '
b11111110001110110001010010111100111100000100011010010110111001 ;
b101110 O
b101110 U
b101110 ^
b101110 _
b11001 8
b11001 =
b11001 F
b11001 G
b10010110000001110101011000101100 %
b10010110000001110101011000101100 D
b10010110000001110101011000101100 j
1)
1*
#146000
b11011001000001110001001010110010 ,
b11011001000001110001001010110010 h
b100 4
b100 6
#150000
0*
#155000
0)
1*
#160000
0*
#165000
b110011 ?
b110011 E
b110011 >
b1100110000011011 @
b1100110000011011 N
b111111100011101 X
b111111100011101 f
b111010 M
b1010001 e
b101110100011001 A
b101110100011001 L
b1000101001011111 Y
b1000101001011111 d
b1000 K
b101010 c
b1000000100100 B
b1000000100100 J
b101010000101101 Z
b101010000101101 b
b1100111 W
b1100111 ]
b1001011 I
b1100111 a
b1100111 V
b1100110000011011010111010001100100010000001001001101001111011100 !
b1100110000011011010111010001100100010000001001001101001111011100 <
b1101001111011100 C
b1101001111011100 H
b1110011100101011 "
b1110011100101011 T
b1110011100101011 [
b1110011100101011 `
b1100110000011011010111010001100111001001001000111100000101101110 '
b1100110000011011010111010001100111001001001000111100000101101110 ;
b11011001000001110001001010110010 %
b11011001000001110001001010110010 D
b11011001000001110001001010110010 j
b1111100 8
b1111100 =
b1111100 F
b1111100 G
b1100 O
b1100 U
b1100 ^
b1100 _
1)
1*
#166000
b110110110110011101010101101101 ,
b110110110110011101010101101101 h
b101 4
b101 6
#170000
0*
#175000
0)
1*
#180000
0*
#185000
b1111000 ?
b1111000 E
b1111000 >
b1010011110111000 X
b1010011110111000 f
b1111111000111 @
b1111111000111 N
b1111110 e
b1000110 M
b111111100011101 Y
b111111100011101 d
b110001010010111 A
b110001010010111 L
b1010001 c
b101011 K
b1000101001011111 Z
b1000101001011111 b
b1101010100001011 B
b1101010100001011 J
b101010 W
b101010 ]
b101010 a
b101010 V
b11110 I
b1111111000111011000101001011111010101000010110111100111001010 !
b1111111000111011000101001011111010101000010110111100111001010 <
b101010000101101 "
b101010000101101 T
b101010000101101 [
b101010000101101 `
b111100111001010 C
b111100111001010 H
b1111111000111011000101001011111100011110100101010110010100111 '
b1111111000111011000101001011111100011110100101010110010100111 ;
b1100111 O
b1100111 U
b1100111 ^
b1100111 _
b110011 8
b110011 =
b110011 F
b110011 G
b110110110110011101010101101101 %
b110110110110011101010101101101 D
b110110110110011101010101101101 j
1)
1*
#186000
b11001111101001011000110010011111 ,
b11001111101001011000110010011111 h
b110 4
b110 6
#190000
0*
#195000
0)
1*
#200000
0*
#205000
b1100110 ?
b1100110 E
b1100110 >
b110011000001101 @
b110011000001101 N
b10000001001001 X
b10000001001001 f
b1110101 M
b1100101 e
b1010111010001100 A
b1010111010001100 L
b1010011110111000 Y
b1010011110111000 d
b10001 K
b1111110 c
b1000100000010010 B
b1000100000010010 J
b111111100011101 Z
b111111100011101 b
b1010001 W
b1010001 ]
b10110 I
b1010001 a
b1010001 V
b110011000001101101011101000110010001000000100100110100111101110 !
b110011000001101101011101000110010001000000100100110100111101110 <
b110100111101110 C
b110100111101110 H
b1000101001011111 "
b1000101001011111 T
b1000101001011111 [
b1000101001011111 `
b110011000001101101011101000110001000111101101111110010101110001 '
b110011000001101101011101000110001000111101101111110010101110001 ;
b11001111101001011000110010011111 %
b11001111101001011000110010011111 D
b11001111101001011000110010011111 j
b1111000 8
b1111000 =
b1111000 F
b1111000 G
b101010 O
b101010 U
b101010 ^
b101010 _
1)
1*
#206000
b111010010011100010101101110100 ,
b111010010011100010101101110100 h
b111 4
b111 6
#210000
0*
#215000
0)
1*
#220000
0*
#225000
b1110000 ?
b1110000 E
b1110000 >
b1011101000110010 X
b1011101000110010 f
b111111100011 @
b111111100011 N
b100 e
b1101 M
b10000001001001 Y
b10000001001001 d
b1011000101001011 A
b1011000101001011 L
b1100101 c
b1010111 K
b1010011110111000 Z
b1010011110111000 b
b1110101010000101 B
b1110101010000101 J
b1111110 W
b1111110 ]
b1111110 a
b1111110 V
b111101 I
b111111100011101100010100101111101010100001011011110011100101 !
b111111100011101100010100101111101010100001011011110011100101 <
b111111100011101 "
b111111100011101 T
b111111100011101 [
b111111100011101 `
b1011110011100101 C
b1011110011100101 H
b111111100011101100010100101111010000110010111001011110010001 '
b111111100011101100010100101111010000110010111001011110010001 ;
b1010001 O
b1010001 U
b1010001 ^
b1010001 _
b1100110 8
b1100110 =
b1100110 F
b1100110 G
b111010010011100010101101110100 %
b111010010011100010101101110100 D
b111010010011100010101101110100 j
1)
1*
#226000
b11010000111110101100100010100001 ,
b11010000111110101100100010100001 h
b1000 4
b1000 6
#230000
0*
#235000
0)
1*
#240000
0*
#245000
b1001101 ?
b1001101 E
b1001101 >
b1011001100000110 @
b1011001100000110 N
b1001100000110110 X
b1001100000110110 f
b1101011 M
b1011101 e
b1101011101000110 A
b1101011101000110 L
b1011101000110010 Y
b1011101000110010 d
b100010 K
b100 c
b100010000001001 B
b100010000001001 J
b10000001001001 Z
b10000001001001 b
b1100101 W
b1100101 ]
b101100 I
b1100101 a
b1100101 V
b1011001100000110110101110100011001000100000010010011010011110111 !
b1011001100000110110101110100011001000100000010010011010011110111 <
b11010011110111 C
b11010011110111 H
b1010011110111000 "
b1010011110111000 T
b1010011110111000 [
b1010011110111000 `
b1011001100000110110101110100011010010100111100111111110001010110 '
b1011001100000110110101110100011010010100111100111111110001010110 ;
b11010000111110101100100010100001 %
b11010000111110101100100010100001 D
b11010000111110101100100010100001 j
b1110000 8
b1110000 =
b1110000 F
b1110000 G
b1111110 O
b1111110 U
b1111110 ^
b1111110 _
1)
1*
#246000
b11011011010111100001010010110110 ,
b11011011010111100001010010110110 h
b1001 4
b1001 6
#250000
0*
#255000
0)
1*
#260000
0*
